README.rst
setup.py
hla/__init__.py
hla/genotyper.bkk.py
hla/genotyper.py
hla/genotyper.test.py
hla/version.py
hla/data/ethnic_priors.txt
hla/data/exon_info_37.bkk.txt
hla/data/exon_info_37.txt
hla/data/exon_info_38.txt
hla/data/hla.dat
hla_genotyper.egg-info/PKG-INFO
hla_genotyper.egg-info/SOURCES.txt
hla_genotyper.egg-info/dependency_links.txt
hla_genotyper.egg-info/entry_points.txt
hla_genotyper.egg-info/not-zip-safe
hla_genotyper.egg-info/requires.txt
hla_genotyper.egg-info/top_level.txt