Metadata-Version: 1.1
Name: hla-genotyper
Version: 0.4.2b1
Summary: Tool to predict HLA genotypes from RNA-Seq and DNA-Seq Data
Home-page: http://github.com/jjfarrell/hla-genotyper
Author: John J. Farrell
Author-email: farrell@bu.edu
License: MIT
Platform: UNKNOWN
Classifier: Development Status :: 4 - Beta
Classifier: Topic :: Scientific/Engineering :: Bio-Informatics
